running_stats/__init__.py
running_stats/py.typed
running_stats/running_stats.py
running_stats-0.2.0.dist-info/WHEEL
running_stats-0.2.0.dist-info/METADATA
running_stats-0.2.0.dist-info/RECORD
