Metadata-Version: 2.3
Name: running-stats
Version: 0.2.0
Summary: Library for computing linear statistics.
Author: Språkbanken Text
Author-email: Språkbanken Text <sb-info@svenska.gu.se>
License: MIT
Classifier: Development Status :: 4 - Beta
Classifier: Intended Audience :: Developers
Classifier: License :: OSI Approved :: MIT License
Classifier: Operating System :: Unix
Classifier: Operating System :: POSIX
Classifier: Programming Language :: Python :: 3.10
Classifier: Programming Language :: Python :: 3.11
Classifier: Programming Language :: Python :: 3.12
Classifier: Programming Language :: Python :: 3.13
Classifier: Programming Language :: Python :: 3.14
Classifier: Programming Language :: Python :: Implementation :: CPython
Classifier: Topic :: Utilities
Requires-Dist: attrs>=25.1.0
Requires-Python: >=3.10
Project-URL: Homepage, https://spraakbanken.gu.se
Project-URL: Issues, https://github.com/spraakbanken/running-stats-py/issues
Project-URL: Repository, https://github.com/spraakbanken/running-stats-py
